<?xml version="1.0" encoding="UTF-8"?>
<mods:mods xmlns:mods="http://www.loc.gov/mods/v3" xmlns="http://www.loc.gov/mods/v3" xmlns:etd="http://www.ndltd.org/standards/metadata/etdms/1.0" xmlns:xsi="http://www.w3.org/2001/XMLSchema-instance" xmlns:xlink="http://www.w3.org/1999/xlink" xmlns:xs="http://www.w3.org/2001/XMLSchema" xsi:schemaLocation="http://www.loc.gov/mods/v3 http://www.loc.gov/standards/mods/v3/mods-3-5.xsd" version="3.5">
  <mods:titleInfo>
    <mods:title>Buried Alive: Analysis of Uncultured Microbes in Marine Sediments</mods:title>
  </mods:titleInfo>
  <mods:name type="personal">
    <mods:namePart type="given">Richard</mods:namePart>
    <mods:namePart type="family">Kevorkian</mods:namePart>
    <mods:role>
      <mods:roleTerm authority="marcrelator" type="text" valueURI="http://id.loc.gov/vocabulary/relators/aut">Author</mods:roleTerm>
    </mods:role>
  </mods:name>
  <mods:originInfo>
    <mods:dateCreated encoding="w3cdtf">2019-06-09T17:00:24-04:00</mods:dateCreated>
    <mods:dateIssued keyDate="yes" encoding="edtf">2019-08</mods:dateIssued>
  </mods:originInfo>
  <mods:recordInfo displayLabel="Submission">
    <mods:recordCreationDate encoding="w3cdtf">2019-06-09T17:00:24-04:00</mods:recordCreationDate>
    <mods:recordChangeDate keyDate="yes" encoding="w3cdtf">2019-06-09T17:00:24-04:00</mods:recordChangeDate>
  </mods:recordInfo>
  <mods:extension>
    <etd:degree>
      <etd:level>Doctoral (includes post-doctoral)</etd:level>
      <etd:name>Doctor of Philosophy</etd:name>
      <etd:discipline>Microbiology</etd:discipline>
      <etd:grantor>University of Tennessee</etd:grantor>
    </etd:degree>
  </mods:extension>
  <mods:name>
    <mods:namePart type="given">Karen</mods:namePart>
    <mods:namePart type="family">Lloyd</mods:namePart>
    <mods:namePart type="termsOfAddress"/>
    <mods:role>
      <mods:roleTerm authority="marcrelator" type="text" valueURI="http://id.loc.gov/vocabulary/relators/ths">Thesis advisor</mods:roleTerm>
    </mods:role>
  </mods:name>
  <mods:name>
    <mods:namePart type="given">Jill</mods:namePart>
    <mods:namePart type="family">Mikucki</mods:namePart>
    <mods:namePart type="termsOfAddress"/>
    <mods:role>
      <mods:roleTerm type="text">Committee member</mods:roleTerm>
    </mods:role>
  </mods:name>
  <mods:name>
    <mods:namePart type="given">Shawn</mods:namePart>
    <mods:namePart type="family">Campagna</mods:namePart>
    <mods:namePart type="termsOfAddress"/>
    <mods:role>
      <mods:roleTerm type="text">Committee member</mods:roleTerm>
    </mods:role>
  </mods:name>
  <mods:name>
    <mods:namePart type="given">Frank</mods:namePart>
    <mods:namePart type="family">Löffler</mods:namePart>
    <mods:namePart type="termsOfAddress"/>
    <mods:role>
      <mods:roleTerm type="text">Committee member</mods:roleTerm>
    </mods:role>
  </mods:name>
  <mods:typeOfResource>text</mods:typeOfResource>
  <mods:genre authority="lcgft" valueURI="http://id.loc.gov/authorities/genreForms/gf2014026039">Academic theses</mods:genre>
  <mods:genre authority="coar" valueURI="http://purl.org/coar/resource_type/c_db06">doctoral thesis</mods:genre>
  <mods:language>
    <mods:languageTerm authority="iso639-2b" type="code">eng</mods:languageTerm>
  </mods:language>
  <mods:abstract>haven't made it yet</mods:abstract>
  <mods:note displayLabel="Submitted Comment">This is a Draft, for review by the Graduate School.</mods:note>
  <mods:relatedItem type="series">
    <mods:titleInfo>
      <mods:title>Graduate Theses and Dissertations</mods:title>
    </mods:titleInfo>
  </mods:relatedItem>
  <mods:note displayLabel="Keywords Submitted by Author"/>
  <mods:accessCondition type="local rights statement"> Unless otherwise noted, (c) 2017 The Author(s).</mods:accessCondition>
<mods:note displayLabel="Copyright holder">author</mods:note><mods:physicalDescription><mods:note displayLabel="Publication Status">PUBLISHED</mods:note></mods:physicalDescription></mods:mods>
